{
  "title": "8SS09.05 कोप–२७ सम्मेलन",
  "presentation_type": "multiple choice",
  "ft": "game",
  "timeLimit": 180,
  "prompts": [
    {
      "question": "कोप–२७ सम्मेलन केसँग सम्बन्धित छ?",
      "correctAns": "जलवायु परिवर्तन",
      "wrongAns": [
        "विश्व व्यापार",
        "अन्तर्राष्ट्रिय खेलकुद",
        "मानव अधिकार"
      ]
    },
    {
      "question": "कोप–२७ सम्मेलन कहिले आयोजना गरिएको थियो?",
      "correctAns": "सन् २०२२",
      "wrongAns": [
        "सन् २०२०",
        "सन् २०२१",
        "सन् २०२३"
      ]
    },
    {
      "question": "कोप–२७ सम्मेलन कहाँ आयोजना गरिएको थियो?",
      "correctAns": "इजिप्ट",
      "wrongAns": [
        "फ्रान्स",
        "भारत",
        "जर्मनी"
      ]
    },
    {
      "question": "कोपको पूर्ण रूप के हो?",
      "correctAns": "Conference of the Parties",
      "wrongAns": [
        "Council of Parties",
        "Committee of People",
        "Climate Organization Program"
      ]
    },
    {
  "question": "कोप सम्मेलन कुन संस्थाअन्तर्गत आयोजना हुन्छ?",
  "correctAns": "संयुक्त राष्ट्र संघ",
  "wrongAns": [
    "विश्व बैंक",
    "विश्व स्वास्थ्य संगठन",
    "सार्क"
  ]
},

    {
      "question": "कोप–२७ सम्मेलनको मुख्य उद्देश्य के हो?",
      "correctAns": "जलवायु परिवर्तनको असर घटाउने उपाय खोज्नु",
      "wrongAns": [
        "व्यापार सम्झौता गर्नु",
        "सैन्य सहयोग बढाउनु",
        "खेलकुद प्रवर्द्धन गर्नु"
      ]
    },
    {
      "question": "कोप–२७ मा विकासशील देशको मुख्य माग के थियो?",
      "correctAns": "जलवायु क्षतिका लागि क्षतिपूर्ति",
      "wrongAns": [
        "हथियार सहयोग",
        "पर्यटन प्रवर्द्धन",
        "शिक्षा सुधार"
      ]
    },
    {
      "question": "नेपाल कोप–२७ सम्मेलनमा किन सहभागी भयो?",
      "correctAns": "जलवायु परिवर्तनबाट परेको असर उठाउन",
      "wrongAns": [
        "व्यापार सम्झौता गर्न",
        "खेलकुद प्रतियोगितामा",
        "सैन्य अभ्यासका लागि"
      ]
    },
    {
  "question": "कोप–२७ मा कुन विषयमा विशेष जोड दिइयो?",
  "correctAns": "हानि र क्षति",
  "wrongAns": [
    "औद्योगिक उत्पादन",
    "सैन्य सुरक्षा",
    "सडक निर्माण"
  ]
},

    {
      "question": "जलवायु परिवर्तनले नेपालमा के असर पारेको छ?",
      "correctAns": "हिमनदी पग्लनु र बाढी पहिरो बढ्नु",
      "wrongAns": [
        "समुद्री आँधी आउनु",
        "मरुभूमि फैलिनु",
        "ज्वालामुखी विस्फोट"
      ]
    },
    {
      "question": "कोप सम्मेलन कति वर्षमा एकपटक आयोजना हुन्छ?",
      "correctAns": "हरेक वर्ष",
      "wrongAns": [
        "हरेक दुई वर्ष",
        "हरेक पाँच वर्ष",
        "दश वर्षमा"
      ]
    },
    {
      "question": "कोप–२७ सम्मेलनको निर्णयले के सन्देश दिएको छ?",
      "correctAns": "जलवायु संकट सबैको साझा समस्या हो",
      "wrongAns": [
        "केवल विकसित देशको समस्या हो",
        "यो अस्थायी समस्या हो",
        "यसको समाधान आवश्यक छैन"
      ]
    }
  ],
  "cl_lo": 8,
  "cl_hi": 8,
  "lang": "np",
  "author": "Bikash Kadayat",
  "subject": [
    "Social Studies"
  ],
  "lot": "SPHS II Lot 5",
  "ch_id": "8SS09.05"
}